{
  "id": "in_honors_g6_0042",
  "domain": null,
  "grade": 6,
  "quarter": null,
  "lesson": null,
  "topic": "circle sectors, fraction to percent conversion",
  "latex": "There are 360 degrees in a circle. If a sector has a central angle of $120^\\circ$, what percentage $n$ of the circle is shaded?",
  "answer_latex": "33\\frac{1}{3}",
  "suggested_quarter": 2,
  "source_file": "Honors_Math_6_20.pdf",
  "source_problem_number": 3,
  "approved": false,
  "flagged": false,
  "honors": true,
  "high_priority": false,
  "notes": ""
}