{
  "id": "les_7p3_g6_0018",
  "domain": "expressions_equations",
  "grade": 6,
  "quarter": 1,
  "lesson": "7.3",
  "topic": "mean and total score equation, word problem",
  "latex": "In a cheerleading competition, each team receives scores in eight categories. One team has a mean score of 7.25 in the eight categories. Write and solve an equation to find the team's total score $s$.",
  "answer_latex": "",
  "suggested_quarter": 2,
  "source_file": "6_7_3.pdf",
  "source_problem_number": 18,
  "approved": true,
  "flagged": false,
  "honors": false,
  "high_priority": false,
  "notes": ""
}